LICENSE.txt
MANIFEST.in
README.md
requirements.txt
setup.py
yamlapi/__init__.py
yamlapi/yaml_api.py
yamlapi.egg-info/PKG-INFO
yamlapi.egg-info/SOURCES.txt
yamlapi.egg-info/dependency_links.txt
yamlapi.egg-info/entry_points.txt
yamlapi.egg-info/not-zip-safe
yamlapi.egg-info/requires.txt
yamlapi.egg-info/top_level.txt
yamlapi/demo/.DS_Store
yamlapi/demo/.dockerignore
yamlapi/demo/.gitignore
yamlapi/demo/.gitlab-ci.yml
yamlapi/demo/Dockerfile
yamlapi/demo/Jenkinsfile
yamlapi/demo/README.md
yamlapi/demo/conftest.py
yamlapi/demo/pytest.ini
yamlapi/demo/requirements.txt
yamlapi/demo/case/__init__.py
yamlapi/demo/case/demo_test.py
yamlapi/demo/resource/demo_one.yaml
yamlapi/demo/resource/demo_three.yaml
yamlapi/demo/resource/demo_two.yaml
yamlapi/demo/setting/__init__.py
yamlapi/demo/setting/project_config.py
yamlapi/demo/tool/__init__.py
yamlapi/demo/tool/beautiful_report_run.py
yamlapi/demo/tool/connect_influx.py
yamlapi/demo/tool/connect_mongo.py
yamlapi/demo/tool/connect_mysql.py
yamlapi/demo/tool/connect_postgresql.py
yamlapi/demo/tool/connect_redis.py
yamlapi/demo/tool/create_random.py
yamlapi/demo/tool/data_type_conversion.py
yamlapi/demo/tool/dingtalk_robot.py
yamlapi/demo/tool/export_test_case.py
yamlapi/demo/tool/feishu_robot.py
yamlapi/demo/tool/function_assistant.py
yamlapi/demo/tool/read_write_json.py
yamlapi/demo/tool/read_write_yaml.py
yamlapi/demo/tool/wechat_robot.py