Metadata-Version: 2.1
Name: yamlapi
Version: 1.4.2
Summary: yamlapi接口测试框架
Home-page: https://github.com/yjlch1016/yamlapi
Author: yangjianliang
Author-email: 526861348@qq.com
License: MIT License
Keywords: Interface test framework
Platform: any
Classifier: Programming Language :: Python :: 3
Classifier: License :: OSI Approved :: MIT License
Classifier: Operating System :: OS Independent
Requires-Python: >=3.5
